{
  "last_attempt": "2026-07-20T03:07:18.682767+05:30",
  "uid": "suz3gT477hWaS4HD8xKCNGtX4hz2",
  "mode": "recent",
  "last_success": "2026-07-20T03:07:28.048189+05:30",
  "counts": {
    "life_ratings": 29,
    "sessions": 17,
    "ratings": 2,
    "monthlyReviews": 1,
    "dfts": 23,
    "captures": 264,
    "weeklyReviews": 1,
    "blocks": 1123,
    "learning": 14,
    "eod": 15,
    "dailyJournal": 52,
    "digest_files": 168,
    "digest_files_changed": 1
  },
  "duration_s": 9.4,
  "last_full": "2026-07-19T06:50:39.639553+05:30"
}